Workbook

Sheet Proof
A1: Proof: AI answers with and without steps, checked against a spreadsheet
A2: An answer is Correct if it is within ₹0.01 of the spreadsheet answer. Yellow cells are the AI answers and can be replaced with your own results from Gemini or ChatGPT; everything else updates automatically. The AI answers shown here were produced by Claude in this chat, not by a separate model (see AI Working).
A4: Method | B4: Correct | C4: Total | D4: Accuracy
A5: Without steps | B5: =COUNTIF(E12:E16,"Correct") -> 3 | C5: =COUNTA(B12:B16) -> 5 | D5: =IF(C5=0,0,B5/C5) -> 0.6
A6: With steps | B6: =COUNTIF(H12:H16,"Correct") -> 5 | C6: =COUNTA(B12:B16) -> 5 | D6: =IF(C6=0,0,B6/C6) -> 1
A8: Result | B8: ="Without steps "&B5&"/"&C5&" vs With steps "&B6&"/"&C6 -> Without steps 3/5 vs With steps 5/5
A10: 5 problems checked
A11: # | B11: Spreadsheet answer | C11: AI without steps | D11: Difference | E11: Result | F11: AI with steps | G11: Difference | H11: Result
A12: 1 | B12: ='Spreadsheet Check'!R5 -> 576999.52 | C12: 575980 | D12: =C12-B12 -> -1019.52 | E12: =IF(C12="","",IF(ABS(C12-B12)<0.01,"Correct","Wrong")) -> Wrong | F12: 576999.52 | G12: =F12-B12 -> 0 | H12: =IF(F12="","",IF(ABS(F12-B12)<0.01,"Correct","Wrong")) -> Correct
A13: 2 | B13: ='Spreadsheet Check'!R6 -> 108416 | C13: 108416 | D13: =C13-B13 -> 0 | E13: =IF(C13="","",IF(ABS(C13-B13)<0.01,"Correct","Wrong")) -> Correct | F13: 108416 | G13: =F13-B13 -> 0 | H13: =IF(F13="","",IF(ABS(F13-B13)<0.01,"Correct","Wrong")) -> Correct
A14: 3 | B14: ='Spreadsheet Check'!R7 -> 86140 | C14: 86376 | D14: =C14-B14 -> 236 | E14: =IF(C14="","",IF(ABS(C14-B14)<0.01,"Correct","Wrong")) -> Wrong | F14: 86140 | G14: =F14-B14 -> 0 | H14: =IF(F14="","",IF(ABS(F14-B14)<0.01,"Correct","Wrong")) -> Correct
A15: 4 | B15: ='Spreadsheet Check'!R8 -> 259256 | C15: 259256 | D15: =C15-B15 -> 0 | E15: =IF(C15="","",IF(ABS(C15-B15)<0.01,"Correct","Wrong")) -> Correct | F15: 259256 | G15: =F15-B15 -> 0 | H15: =IF(F15="","",IF(ABS(F15-B15)<0.01,"Correct","Wrong")) -> Correct
A16: 5 | B16: ='Spreadsheet Check'!R9 -> 244849.5 | C16: 244849.5 | D16: =C16-B16 -> 0 | E16: =IF(C16="","",IF(ABS(C16-B16)<0.01,"Correct","Wrong")) -> Correct | F16: 244849.5 | G16: =F16-B16 -> 0 | H16: =IF(F16="","",IF(ABS(F16-B16)<0.01,"Correct","Wrong")) -> Correct

Sheet Problems
A1: 5 Money Problems (discount + GST + freight)
A3: # | B3: Problem
A4: 1 | B4: A customer orders 1,200 units at ₹450 each. Orders above 1,000 units get 8% off. Loyal customers get an extra 2% off the discounted price. Then add 18% GST. Freight of ₹2,500 is added at the end and has no GST. What is the invoice total?
A5: 2 | B5: A shop buys 80 laptop bags at ₹1,250 each. Orders above 50 units get 5% off. Freight of ₹1,800 is added before GST and is taxable. GST is 12%. What is the invoice total?
A6: 3 | B6: A company orders 250 units at ₹320 each. Orders above 200 units get 10% off. A coupon then takes ₹2,000 off the discounted price. GST of 18% applies to the goods. Freight of ₹3,000 also carries 18% GST. What is the invoice total?
A7: 4 | B7: An office orders 60 chairs at ₹4,200 each. Orders with a value above ₹200,000 get 15% off. Add 18% GST on the discounted price. Freight of ₹6,500 is added at the end and has no GST. What is the invoice total?
A8: 5 | B8: A dealer buys 15 machines at ₹18,500 each. A festival offer gives 12% off. Paying in advance gives an extra 5% off the discounted price. Freight of ₹1,200 is added before GST and is taxable. GST is 5%. What is the invoice total?

Sheet Spreadsheet Check
A1: Spreadsheet Check: the correct answers, calculated with formulas
A2: Blue cells are the numbers from each problem. Everything else is a formula. Order of rules: volume discount → extra % off → coupon → taxable freight → GST → untaxed freight.
A4: # | B4: Qty | C4: Unit price (₹) | D4: Gross (₹) | E4: Discount rule applies to | F4: Threshold | G4: Discount % | H4: Discount amount (₹) | I4: After discount (₹) | J4: Extra % off | K4: After extra (₹) | L4: Coupon (₹ off) | M4: Taxable freight (₹) | N4: Taxable base (₹) | O4: GST % | P4: GST amount (₹) | Q4: Freight, no GST (₹) | R4: CORRECT TOTAL (₹)
A5: 1 | B5: 1200 | C5: 450 | D5: =B5*C5 -> 540000 | E5: Qty | F5: 1000 | G5: 0.08 | H5: =IF(OR(E5="None",AND(E5="Qty",B5>F5),AND(E5="Value",D5>F5)),D5*G5,0) -> 43200 | I5: =D5-H5 -> 496800 | J5: 0.02 | K5: =I5*(1-J5) -> 486864 | L5: 0 | M5: 0 | N5: =K5-L5+M5 -> 486864 | O5: 0.18 | P5: =N5*O5 -> 87635.52 | Q5: 2500 | R5: =ROUND(N5+P5+Q5,2) -> 576999.52
A6: 2 | B6: 80 | C6: 1250 | D6: =B6*C6 -> 100000 | E6: Qty | F6: 50 | G6: 0.05 | H6: =IF(OR(E6="None",AND(E6="Qty",B6>F6),AND(E6="Value",D6>F6)),D6*G6,0) -> 5000 | I6: =D6-H6 -> 95000 | J6: 0 | K6: =I6*(1-J6) -> 95000 | L6: 0 | M6: 1800 | N6: =K6-L6+M6 -> 96800 | O6: 0.12 | P6: =N6*O6 -> 11616 | Q6: 0 | R6: =ROUND(N6+P6+Q6,2) -> 108416
A7: 3 | B7: 250 | C7: 320 | D7: =B7*C7 -> 80000 | E7: Qty | F7: 200 | G7: 0.1 | H7: =IF(OR(E7="None",AND(E7="Qty",B7>F7),AND(E7="Value",D7>F7)),D7*G7,0) -> 8000 | I7: =D7-H7 -> 72000 | J7: 0 | K7: =I7*(1-J7) -> 72000 | L7: 2000 | M7: 3000 | N7: =K7-L7+M7 -> 73000 | O7: 0.18 | P7: =N7*O7 -> 13140 | Q7: 0 | R7: =ROUND(N7+P7+Q7,2) -> 86140
A8: 4 | B8: 60 | C8: 4200 | D8: =B8*C8 -> 252000 | E8: Value | F8: 200000 | G8: 0.15 | H8: =IF(OR(E8="None",AND(E8="Qty",B8>F8),AND(E8="Value",D8>F8)),D8*G8,0) -> 37800 | I8: =D8-H8 -> 214200 | J8: 0 | K8: =I8*(1-J8) -> 214200 | L8: 0 | M8: 0 | N8: =K8-L8+M8 -> 214200 | O8: 0.18 | P8: =N8*O8 -> 38556 | Q8: 6500 | R8: =ROUND(N8+P8+Q8,2) -> 259256
A9: 5 | B9: 15 | C9: 18500 | D9: =B9*C9 -> 277500 | E9: None | F9: 0 | G9: 0.12 | H9: =IF(OR(E9="None",AND(E9="Qty",B9>F9),AND(E9="Value",D9>F9)),D9*G9,0) -> 33300 | I9: =D9-H9 -> 244200 | J9: 0.05 | K9: =I9*(1-J9) -> 231990 | L9: 0 | M9: 1200 | N9: =K9-L9+M9 -> 233190 | O9: 0.05 | P9: =N9*O9 -> 11659.5 | Q9: 0 | R9: =ROUND(N9+P9+Q9,2) -> 244849.5

Sheet AI Working
A1: AI Working: why answers differed
A3: # | B3: Without steps: what went wrong | C3: With steps: the working shown by the AI
A4: 1 | B4: Added the two discounts (8% + 2% = 10%) instead of taking 2% off the already-discounted price. | C4: 1. Base: 1,200 × ₹450.00 = ₹540,000.00 2. 8% discount: -₹43,200.00 → ₹496,800.00 3. Extra 2% off the discounted price: -₹9,936.00 → ₹486,864.00 4. GST 18% on ₹486,864.00: +₹87,635.52 → ₹574,499.52 5. Add freight (no GST) ₹2,500.00 → ₹576,999.52 Final amount: ₹576,999.52
A5: 2 | B5: Nothing wrong. The answer matches the spreadsheet. | C5: 1. Base: 80 × ₹1,250.00 = ₹100,000.00 2. 5% discount: -₹5,000.00 → ₹95,000.00 3. Add taxable freight ₹1,800.00 → ₹96,800.00 4. GST 12% on ₹96,800.00: +₹11,616.00 → ₹108,416.00 Final amount: ₹108,416.00
A6: 3 | B6: Took the ₹2,000 coupon off before the 10% discount instead of after it. | C6: 1. Base: 250 × ₹320.00 = ₹80,000.00 2. 10% discount: -₹8,000.00 → ₹72,000.00 3. Coupon -₹2,000.00 → ₹70,000.00 4. Add taxable freight ₹3,000.00 → ₹73,000.00 5. GST 18% on ₹73,000.00: +₹13,140.00 → ₹86,140.00 Final amount: ₹86,140.00
A7: 4 | B7: Nothing wrong. The answer matches the spreadsheet. | C7: 1. Base: 60 × ₹4,200.00 = ₹252,000.00 2. 15% discount: -₹37,800.00 → ₹214,200.00 3. GST 18% on ₹214,200.00: +₹38,556.00 → ₹252,756.00 4. Add freight (no GST) ₹6,500.00 → ₹259,256.00 Final amount: ₹259,256.00
A8: 5 | B8: Nothing wrong. The answer matches the spreadsheet. | C8: 1. Base: 15 × ₹18,500.00 = ₹277,500.00 2. 12% discount: -₹33,300.00 → ₹244,200.00 3. Extra 5% off the discounted price: -₹12,210.00 → ₹231,990.00 4. Add taxable freight ₹1,200.00 → ₹233,190.00 5. GST 5% on ₹233,190.00: +₹11,659.50 → ₹244,849.50 Final amount: ₹244,849.50

Sheet Prompts
A1: Prompts to paste into the AI (use a new chat for each)
A3: PROMPT A: Without steps
A4: Solve each problem below. Give only the final invoice total for each, with no working.
A5: Problem 1: A customer orders 1,200 units at ₹450 each. Orders above 1,000 units get 8% off. Loyal customers get an extra 2% off the discounted price. Then add 18% GST. Freight of ₹2,500 is added at the end and has no GST. What is the invoice total?
A6: Problem 2: A shop buys 80 laptop bags at ₹1,250 each. Orders above 50 units get 5% off. Freight of ₹1,800 is added before GST and is taxable. GST is 12%. What is the invoice total?
A7: Problem 3: A company orders 250 units at ₹320 each. Orders above 200 units get 10% off. A coupon then takes ₹2,000 off the discounted price. GST of 18% applies to the goods. Freight of ₹3,000 also carries 18% GST. What is the invoice total?
A8: Problem 4: An office orders 60 chairs at ₹4,200 each. Orders with a value above ₹200,000 get 15% off. Add 18% GST on the discounted price. Freight of ₹6,500 is added at the end and has no GST. What is the invoice total?
A9: Problem 5: A dealer buys 15 machines at ₹18,500 each. A festival offer gives 12% off. Paying in advance gives an extra 5% off the discounted price. Freight of ₹1,200 is added before GST and is taxable. GST is 5%. What is the invoice total?
A11: PROMPT B: With steps (the magic line)
A12: Work step by step. Show each rule you apply and the running total. Give the final amount last.
A13: Problem 1: A customer orders 1,200 units at ₹450 each. Orders above 1,000 units get 8% off. Loyal customers get an extra 2% off the discounted price. Then add 18% GST. Freight of ₹2,500 is added at the end and has no GST. What is the invoice total?
A14: Problem 2: A shop buys 80 laptop bags at ₹1,250 each. Orders above 50 units get 5% off. Freight of ₹1,800 is added before GST and is taxable. GST is 12%. What is the invoice total?
... A17: Problem 5: A dealer buys 15 machines at ₹18,500 each. A festival offer gives 12% off. Paying in advance gives an extra 5% off the discounted price. Freight of ₹1,200 is added before GST and is taxable. GST is 5%. What is the invoice total?
